odoo10_addon_mrp_bom_note-10.0.1.0.0-py2.7-nspkg.pth
odoo/addons/mrp_bom_note/README.rst
odoo/addons/mrp_bom_note/__init__.py
odoo/addons/mrp_bom_note/__manifest__.py
odoo/addons/mrp_bom_note/i18n/de.po
odoo/addons/mrp_bom_note/i18n/es.po
odoo/addons/mrp_bom_note/i18n/mrp_bom_notes.pot
odoo/addons/mrp_bom_note/i18n/pt_BR.po
odoo/addons/mrp_bom_note/i18n/zh_CN.po
odoo/addons/mrp_bom_note/models/__init__.py
odoo/addons/mrp_bom_note/models/mrp_bom.py
odoo/addons/mrp_bom_note/views/mrp_bom_view.xml
odoo10_addon_mrp_bom_note-10.0.1.0.0.dist-info/DESCRIPTION.rst
odoo10_addon_mrp_bom_note-10.0.1.0.0.dist-info/METADATA
odoo10_addon_mrp_bom_note-10.0.1.0.0.dist-info/RECORD
odoo10_addon_mrp_bom_note-10.0.1.0.0.dist-info/WHEEL
odoo10_addon_mrp_bom_note-10.0.1.0.0.dist-info/metadata.json
odoo10_addon_mrp_bom_note-10.0.1.0.0.dist-info/namespace_packages.txt
odoo10_addon_mrp_bom_note-10.0.1.0.0.dist-info/top_level.txt
