Metadata-Version: 2.0
Name: odoo10-addon-mrp-bom-note
Version: 10.0.1.0.0
Summary: Notes in Bill of Materials
Home-page: http://www.odoomrp.com
Author: OdooMRP team,AvanzOSC,Serv. Tecnol. Avanzados - Pedro M. Baeza, Odoo Community Association (OCA)
Author-email: support@odoo-community.org
License: UNKNOWN
Platform: UNKNOWN
Classifier: Programming Language :: Python
Classifier: Framework :: Odoo
Requires-Python: ~=2.7
Requires-Dist: odoo (<10.1dev,>=10.0)
